{
  "output": "{\n  \"status\": \"fail\",\n  \"test_framework\": \"vitest\",\n  \"test_results\": {\n    \"passed\": 0,\n    \"failed\": 3,\n    \"skipped\": 0\n  },\n  \"failed_tests\": [\n    {\n      \"name\": \"config loader should load values in correct priority order\",\n      \"error\": \"Error: Cannot find module '../src/config/index.ts' from '/tmp/test-runner-12345/src/config/__tests__/configLoader.test.ts'\",\n      \"stack\": \"Error: Cannot find module '../src/config/index.ts' from '/tmp/test-runner-12345/src/config/__tests__/configLoader.test.ts'\\n    at Resolver.resolveModule (/tmp/test-runner-12345/node_modules/vite/node_modules/jest-resolve/build/index.js:306:11)\\n    at /tmp/test-runner-12345/src/config/__tests__/configLoader.test.ts:1:1\\n    at /tmp/test-runner-12345/src/config/__tests__/configLoader.test.ts:1:1\",\n      \"file\": \"/tmp/test-runner-12345/src/config/__tests__/configLoader.test.ts\"\n    },\n    {\n      \"name\": \"config loader should validate JSON schema\",\n      \"error\": \"Error: Cannot find module '../src/config/index.ts' from '/tmp/test-runner-12345/src/config/__tests__/configLoader.test.ts'\",\n      \"stack\": \"Error: Cannot find module '../src/config/index.ts' from '/tmp/test-runner-12345/src/config/__tests__/configLoader.test.ts'\\n    at Resolver.resolveModule (/tmp/test-runner-12345/node_modules/vite/node_modules/jest-resolve/build/index.js:306:11)\\n    at /tmp/test-runner-12345/src/config/__tests__/configLoader.test.ts:1:1\\n    at /tmp/test-runner-12345/src/config/__tests__/configLoader.test.ts:1:1\",\n      \"file\": \"/tmp/test-runner-12345/src/config/__tests__/configLoader.test.ts\"\n    },\n    {\n      \"name\": \"default config should provide correct defaults\",\n      \"error\": \"Error: Cannot find module '../src/config/defaultConfig.ts' from '/tmp/test-runner-12345/src/config/__tests__/configLoader.test.ts'\",\n      \"stack\": \"Error: Cannot find module '../src/config/defaultConfig.ts' from '/tmp/test-runner-12345/src/config/__tests__/configLoader.test.ts'\\n    at Resolver.resolveModule (/tmp/test-runner-12345/node_modules/vite/node_modules/jest-resolve/build/index.js:306:11)\\n    at /tmp/test-runner-12345/src/config/__tests__/configLoader.test.ts:1:1\\n    at /tmp/test-runner-12345/src/config/__tests__/configLoader.test.ts:1:1\",\n      \"file\": \"/tmp/test-runner-12345/src/config/__tests__/configLoader.test.ts\"\n    }\n  ],\n  \"root_causes\": [\n    {\n      \"type\": \"missing_files\",\n      \"description\": \"Required config files (src/config/index.ts, src/config/defaultConfig.ts) are missing from the project\",\n      \"impact\": \"All tests fail due to module resolution errors\"\n    },\n    {\n      \"type\": \"configuration_issue\",\n      \"description\": \"Test files reference modules that do not exist in the project structure\",\n      \"impact\": \"Cannot execute any tests without proper file structure\"\n    }\n  ],\n  \"linter_results\": {\n    \"eslint\": {\n      \"errors\": 0,\n      \"warnings\": 0\n    },\n    \"tslint\": {\n      \"errors\": 0,\n      \"warnings\": 0\n    }\n  },\n  \"coverage_analysis\": {\n    \"status\": \"fail\",\n    \"details\": [\n      {\n        \"requirement\": \"Config loads values in correct priority order\",\n        \"covered\": false,\n        \"reason\": \"Missing implementation of config loader\"\n      },\n      {\n        \"requirement\": \"JSON schema validation passes for valid configs\",\n        \"covered\": false,\n        \"reason\": \"Missing implementation of schema validation\"\n      },\n      {\n        \"requirement\": \"Validation fails appropriately for invalid configs\",\n        \"covered\": false,\n        \"reason\": \"Missing implementation of schema validation\"\n      },\n      {\n        \"requirement\": \"Default values are applied when not specified\",\n        \"covered\": false,\n        \"reason\": \"Missing implementation of default config\"\n      },\n      {\n        \"requirement\": \"Example file includes all configurable options\",\n        \"covered\": false,\n        \"reason\": \"Missing .example.env file\"\n      },\n      {\n        \"requirement\": \"Default paths for logs are correctly set\",\n        \"covered\": false,\n        \"reason\": \"Missing implementation of default config\"\n      },\n      {\n        \"requirement\": \"Default store configuration is properly defined\",\n        \"covered\": false,\n        \"reason\": \"Missing implementation of default config\"\n      },\n      {\n        \"requirement\": \"LM Studio endpoint defaults to localhost:1234\",\n        \"covered\": false,\n        \"reason\": \"Missing implementation of default config\"\n      }\n    ]\n  },\n  \"critical_findings\": [\n    {\n      \"severity\": \"SEVERE\",\n      \"description\": \"Missing core implementation files (src/config/index.ts, src/config/defaultConfig.ts) prevent any test execution\",\n      \"impact\": \"Complete test coverage gap for all planned features\"\n    }\n  ],\n  \"recommendations\": [\n    \"Create the missing config loader implementation in src/config/index.ts\",\n    \"Implement default configuration values in src/config/defaultConfig.ts\",\n    \"Create the example environment file .example.env\",\n    \"Ensure proper module resolution in test configuration\"\n  ]\n}",
  "duration_ms": 25530
}