{
  "output": "```json\n{\n  \"summary\": \"The QA review of vitest.config.ts failed due to an expected ';'\nbut found ':' error, which prevents further review progress.\",\n  \"hypotheses\": [\n    {\n      \"id\": \"H1\",\n      \"statement\": \"The syntax issue in vitest.config.ts at line 18 is caused by a missing semicolon.\",\n      \"confidence\": \"high\",\n      \"evidence\": [\"Review feedback: File vitest.config.ts has an error at line 18: Expected ';'\nbut found ':'.\"],\n      \"affected_components\": [\"src/vitest.config.ts\"],\n      \"remediation_steps\": [\n        \"Add a semicolon to the end of the configuration settings in vitest.config.ts.\",\n        \"Verify that no other syntax errors exist in the file.\"\n      ],\n      \"acceptance_criteria\": [\n        \"The updated file should compile without errors and pass all tests.\",\n        \"Review feedback should be resolved.\"\n      ],\n      \"validation_steps\": [\n        \"Run `npm install` followed by `vitest run` to verify that the configuration is correct.\",\n        \"Verify that the review feedback has been addressed.\"\n      ],\n      \"priority\": \"critical\"\n    }\n  ],\n  \"action_plan\": {\n    \"title\": \"Resolve Syntax Error in vitest.config.ts\",\n    \"summary\": \"Add a semicolon to the end of the configuration settings in vitest.config.ts and verify no other syntax errors exist.\",\n    \"steps\": [\n      \"Locate line 18 in vitest.config.ts and add a semicolon at the end of the configuration settings.\",\n      \"Run `npm install` followed by `vitest run` to verify that the updated file compiles without errors.\"\n    ],\n    \"acceptance_criteria\": [\n      \"The updated file should compile without errors and pass all tests.\",\n      \"Review feedback should be resolved.\"\n    ],\n    \"validation_plan\": [\"Run `npm install` followed by `vitest run` to verify that the configuration is correct.\"],\n    \"key_files\": [\"src/vitest.config.ts\"],\n    \"priority\": \"critical\",\n    \"labels\": [\"qa_follow_up\", \"syntax_error\"]\n  }\n}\n```",
  "duration_ms": 23484
}