{
  "repo": "/mnt/e/code/machine-client-log-summarizer",
  "generated_at": "2025-10-07T02:17:48.992Z",
  "totals": {
    "files": 5,
    "bytes": 3162,
    "lines": 142
  },
  "components": [
    {
      "component": ".",
      "totals": {
        "files": 5,
        "bytes": 3162,
        "lines": 142
      },
      "largest": [
        {
          "path": "src/styles.css",
          "bytes": 1063,
          "mtime": 1759803468863.1584,
          "lines": 63,
          "sha1": "1f9eaba044900499ecfa47757966aa97e640eee5"
        },
        {
          "path": "src/ingest/fileIngest.ts",
          "bytes": 662,
          "mtime": 1759803468862.1538,
          "lines": 26,
          "sha1": "d7f980a5b3a2801c44bc0b6780b4639801982990"
        },
        {
          "path": "src/App.test.tsx",
          "bytes": 657,
          "mtime": 1759803468860.1704,
          "lines": 21,
          "sha1": "67b4f8b62ddcb1df0fb572b6e538a6a9d82f5a0e"
        },
        {
          "path": "src/App.tsx",
          "bytes": 578,
          "mtime": 1759803468861.101,
          "lines": 23,
          "sha1": "0dc11a01fc0152cce54a439feab2189cb41d450c"
        },
        {
          "path": "src/main.tsx",
          "bytes": 202,
          "mtime": 1759613861163.0193,
          "lines": 9,
          "sha1": "983ba3ef5440a072bd0a4f28ea1473a136fcf549"
        }
      ],
      "longest": [
        {
          "path": "src/styles.css",
          "bytes": 1063,
          "mtime": 1759803468863.1584,
          "lines": 63,
          "sha1": "1f9eaba044900499ecfa47757966aa97e640eee5"
        },
        {
          "path": "src/ingest/fileIngest.ts",
          "bytes": 662,
          "mtime": 1759803468862.1538,
          "lines": 26,
          "sha1": "d7f980a5b3a2801c44bc0b6780b4639801982990"
        },
        {
          "path": "src/App.tsx",
          "bytes": 578,
          "mtime": 1759803468861.101,
          "lines": 23,
          "sha1": "0dc11a01fc0152cce54a439feab2189cb41d450c"
        },
        {
          "path": "src/App.test.tsx",
          "bytes": 657,
          "mtime": 1759803468860.1704,
          "lines": 21,
          "sha1": "67b4f8b62ddcb1df0fb572b6e538a6a9d82f5a0e"
        },
        {
          "path": "src/main.tsx",
          "bytes": 202,
          "mtime": 1759613861163.0193,
          "lines": 9,
          "sha1": "983ba3ef5440a072bd0a4f28ea1473a136fcf549"
        }
      ]
    }
  ],
  "hotspots": {
    "largest_files": [
      {
        "path": "src/styles.css",
        "bytes": 1063,
        "mtime": 1759803468863.1584,
        "lines": 63,
        "sha1": "1f9eaba044900499ecfa47757966aa97e640eee5"
      },
      {
        "path": "src/ingest/fileIngest.ts",
        "bytes": 662,
        "mtime": 1759803468862.1538,
        "lines": 26,
        "sha1": "d7f980a5b3a2801c44bc0b6780b4639801982990"
      },
      {
        "path": "src/App.test.tsx",
        "bytes": 657,
        "mtime": 1759803468860.1704,
        "lines": 21,
        "sha1": "67b4f8b62ddcb1df0fb572b6e538a6a9d82f5a0e"
      },
      {
        "path": "src/App.tsx",
        "bytes": 578,
        "mtime": 1759803468861.101,
        "lines": 23,
        "sha1": "0dc11a01fc0152cce54a439feab2189cb41d450c"
      },
      {
        "path": "src/main.tsx",
        "bytes": 202,
        "mtime": 1759613861163.0193,
        "lines": 9,
        "sha1": "983ba3ef5440a072bd0a4f28ea1473a136fcf549"
      }
    ],
    "longest_files": [
      {
        "path": "src/styles.css",
        "bytes": 1063,
        "mtime": 1759803468863.1584,
        "lines": 63,
        "sha1": "1f9eaba044900499ecfa47757966aa97e640eee5"
      },
      {
        "path": "src/ingest/fileIngest.ts",
        "bytes": 662,
        "mtime": 1759803468862.1538,
        "lines": 26,
        "sha1": "d7f980a5b3a2801c44bc0b6780b4639801982990"
      },
      {
        "path": "src/App.tsx",
        "bytes": 578,
        "mtime": 1759803468861.101,
        "lines": 23,
        "sha1": "0dc11a01fc0152cce54a439feab2189cb41d450c"
      },
      {
        "path": "src/App.test.tsx",
        "bytes": 657,
        "mtime": 1759803468860.1704,
        "lines": 21,
        "sha1": "67b4f8b62ddcb1df0fb572b6e538a6a9d82f5a0e"
      },
      {
        "path": "src/main.tsx",
        "bytes": 202,
        "mtime": 1759613861163.0193,
        "lines": 9,
        "sha1": "983ba3ef5440a072bd0a4f28ea1473a136fcf549"
      }
    ]
  }
}
